howard/__init__.py
howard/defaults.py
howard/utils.py
howard/issuers/__init__.py
howard/issuers/certificate.py
howard/issuers/invoice.py
howard/issuers/realisation.py
howard/locale/fr_FR/LC_MESSAGES/django.mo
howard/locale/fr_FR/LC_MESSAGES/django.po
howard/static/howard/logo-edx.svg
howard/static/howard/logo-fun.png
howard/static/howard/logo-ministere-travail.svg
howard/static/howard/test-signature.png
howard/templates/howard/certificate.css
howard/templates/howard/certificate.html
howard/templates/howard/invoice.css
howard/templates/howard/invoice.html
howard/templates/howard/realisation.css
howard/templates/howard/realisation.html
howard/templatetags/__init__.py
howard/templatetags/howard_tags.py
django_marion_howard-0.6.0.dist-info/METADATA
django_marion_howard-0.6.0.dist-info/WHEEL
django_marion_howard-0.6.0.dist-info/top_level.txt
django_marion_howard-0.6.0.dist-info/zip-safe
django_marion_howard-0.6.0.dist-info/RECORD
