Metadata-Version: 2.1
Name: django-marion-howard
Version: 0.6.0
Summary: FUN documents for Marion, the documents factory
Home-page: https://github.com/openfun/marion
Author: Open FUN (France Universite Numerique)
Author-email: fun.dev@fun-mooc.fr
License: MIT
Keywords: Django,LMS,learning,PDF
Classifier: Development Status :: 4 - Beta
Classifier: Framework :: Django
Classifier: Framework :: Django :: 3.1
Classifier: Framework :: Django :: 3.2
Classifier: Intended Audience :: Developers
Classifier: License :: OSI Approved :: MIT License
Classifier: Natural Language :: English
Classifier: Programming Language :: Python :: 3
Classifier: Programming Language :: Python :: 3.8
Requires-Dist: django-marion >=0.6.0
